twitter_cleanse/__init__.py
twitter_cleanse/cleanse.py
twitter_cleanse/metadata.py
twitter_cleanse-0.2.0.data/scripts/twitter-cleanse
twitter_cleanse-0.2.0.dist-info/LICENSE
twitter_cleanse-0.2.0.dist-info/METADATA
twitter_cleanse-0.2.0.dist-info/NOTICE
twitter_cleanse-0.2.0.dist-info/WHEEL
twitter_cleanse-0.2.0.dist-info/top_level.txt
twitter_cleanse-0.2.0.dist-info/RECORD
