Metadata-Version: 2.1
Name: twitter-cleanse
Version: 0.2.0
Summary: Clean up your Twitter follow list.
Home-page: https://github.com/dlo/twitter_cleanse
Author: Dan Loewenherz
Author-email: dan@lionheartsw.com
License: Apache 2.0
Platform: UNKNOWN
Classifier: Development Status :: 5 - Production/Stable
Classifier: Environment :: Console
Classifier: Intended Audience :: End Users/Desktop
Classifier: License :: OSI Approved :: Apache Software License
Classifier: Natural Language :: English
Classifier: Natural Language :: English
Classifier: Operating System :: OS Independent
Classifier: Programming Language :: Python :: 2.6
Classifier: Programming Language :: Python :: 2.7
Classifier: Programming Language :: Python
Classifier: Topic :: Software Development :: Libraries :: Python Modules
Classifier: Topic :: Utilities
Requires-Dist: python-dateutil
Requires-Dist: pytz
Requires-Dist: requests-oauthlib
Requires-Dist: restmapper
